README.md
px
setup.py
Phoenix_Cli.egg-info/PKG-INFO
Phoenix_Cli.egg-info/SOURCES.txt
Phoenix_Cli.egg-info/dependency_links.txt
Phoenix_Cli.egg-info/requires.txt
Phoenix_Cli.egg-info/top_level.txt
phoenix/__init__.py
phoenix/cli/__init__.py
phoenix/cli/__main__.py
phoenix/cli/commands/__init__.py
phoenix/cli/commands/data.py
phoenix/cli/commands/data_help.py
phoenix_cli.egg-info/PKG-INFO
phoenix_cli.egg-info/SOURCES.txt
phoenix_cli.egg-info/dependency_links.txt
phoenix_cli.egg-info/requires.txt
phoenix_cli.egg-info/top_level.txt